mindsdk/Constants.py
mindsdk/__init__.py
mindsdk/Mapper/Mapper.py
mindsdk/Mapper/__init__.py
mindsdk/Mind/Mind.py
mindsdk/Mind/Offline.py
mindsdk/Mind/Online.py
mindsdk/Mind/__init__.py
mindsdk/WS/WS.py
mindsdk/WS/__init__.py
mapnamindsdk-0.1.6.dist-info/METADATA
mapnamindsdk-0.1.6.dist-info/WHEEL
mapnamindsdk-0.1.6.dist-info/top_level.txt
mapnamindsdk-0.1.6.dist-info/RECORD
