Metadata-Version: 2.1
Name: mapnamindsdk
Version: 0.1.6
Summary: Mapna MIND Software Development Kit
Home-page: https://www.mapnaec.com
Author: Soheil Mehralian, Homa Hasannezhad
Author-email: mehralian1@gmail.com
License: UNKNOWN
Platform: UNKNOWN
Classifier: Programming Language :: Python :: 3
Classifier: License :: OSI Approved :: MIT License
Classifier: Operating System :: OS Independent
Requires-Python: >=3
